odoo/addons/shopinvader_auth_jwt/README.rst
odoo/addons/shopinvader_auth_jwt/__init__.py
odoo/addons/shopinvader_auth_jwt/__manifest__.py
odoo/addons/shopinvader_auth_jwt/components/__init__.py
odoo/addons/shopinvader_auth_jwt/components/service_context_provider.py
odoo/addons/shopinvader_auth_jwt/controllers/__init__.py
odoo/addons/shopinvader_auth_jwt/controllers/main.py
odoo/addons/shopinvader_auth_jwt/i18n/shopinvader_auth_jwt.pot
odoo/addons/shopinvader_auth_jwt/models/__init__.py
odoo/addons/shopinvader_auth_jwt/models/shopinvader_backend.py
odoo/addons/shopinvader_auth_jwt/readme/CONTRIBUTORS.rst
odoo/addons/shopinvader_auth_jwt/readme/DESCRIPTION.rst
odoo/addons/shopinvader_auth_jwt/static/description/index.html
odoo/addons/shopinvader_auth_jwt/views/shopinvader_backend.xml
odoo14_addon_shopinvader_auth_jwt-14.0.1.2.0.dist-info/METADATA
odoo14_addon_shopinvader_auth_jwt-14.0.1.2.0.dist-info/WHEEL
odoo14_addon_shopinvader_auth_jwt-14.0.1.2.0.dist-info/top_level.txt
odoo14_addon_shopinvader_auth_jwt-14.0.1.2.0.dist-info/RECORD
